loopialib/__init__.py
loopialib/_compat.py
loopialib/client.py
loopialib/exceptions.py
loopialib/types.py
loopialib/utils.py
loopialib-0.2.0.dist-info/DESCRIPTION.rst
loopialib-0.2.0.dist-info/METADATA
loopialib-0.2.0.dist-info/metadata.json
loopialib-0.2.0.dist-info/RECORD
loopialib-0.2.0.dist-info/top_level.txt
loopialib-0.2.0.dist-info/WHEEL
