Metadata-Version: 2.0
Name: loopialib
Version: 0.2.0
Summary: A pythonic interface to Loopia's XMLRPCAPI
Home-page: https://www.github.com/runfalk/loopialib
Author: Andreas Runfalk
Author-email: andreas@runfalk.se
License: MIT
Platform: UNKNOWN
Classifier: Development Status :: 3 - Alpha
Classifier: Intended Audience :: Developers
Classifier: License :: OSI Approved :: MIT License
Classifier: Programming Language :: Python
Classifier: Programming Language :: Python :: 2
Classifier: Programming Language :: Python :: 3
Classifier: Topic :: Utilities
Provides-Extra: dev
Requires-Dist: mock; extra == 'dev'
Requires-Dist: pytest; extra == 'dev'
Requires-Dist: pytest-cov; extra == 'dev'
